fcm_devices/__init__.py
fcm_devices/admin.py
fcm_devices/apps.py
fcm_devices/fcm.py
fcm_devices/models.py
fcm_devices/service.py
fcm_devices/settings.py
fcm_devices/signals.py
fcm_devices/api/__init__.py
fcm_devices/api/drf/__init__.py
fcm_devices/api/drf/serializers.py
fcm_devices/api/drf/views.py
fcm_devices/migrations/0001_initial.py
fcm_devices/migrations/__init__.py
django_fcm_devices-1.0.2.dist-info/LICENSE
django_fcm_devices-1.0.2.dist-info/METADATA
django_fcm_devices-1.0.2.dist-info/WHEEL
django_fcm_devices-1.0.2.dist-info/top_level.txt
django_fcm_devices-1.0.2.dist-info/RECORD
