Metadata-Version: 2.1
Name: django-fcm-devices
Version: 1.0.2
Summary: Minimalistic device registration and push notifications with FCM and Django
Home-page: https://github.com/lukeburden/django-fcm-devices
Author: Luke Burden
Author-email: lukeburden@gmail.com
License: MIT
Platform: UNKNOWN
Classifier: Development Status :: 5 - Production/Stable
Classifier: Environment :: Web Environment
Classifier: Intended Audience :: Developers
Classifier: License :: OSI Approved :: MIT License
Classifier: Operating System :: OS Independent
Classifier: Programming Language :: Python
Classifier: Programming Language :: Python :: 3
Classifier: Framework :: Django
Requires-Dist: django (<4,>=3)
Requires-Dist: pyfcm (<1.6,>=1.4)
Requires-Dist: django-konst (<3,>=2)
